[
  {
    "Course Name": "American Government: Constitutional Foundations",
    "description": "Explore the constitutional foundations of American government and political institutions",
    "university": "Harvard University",
    "Fees": "$49,000",
    "Duration": "12 weeks",
    "Level": "Undergraduate"
  },
  {
    "Course Name": "CRISPR: Gene-editing Applications",
    "description": "Learn about CRISPR technology and its revolutionary applications in gene editing",
    "university": "Harvard University",
    "Fees": "$2,500",
    "Duration": "8 weeks",
    "Level": "Certificate"
  },
  {
    "Course Name": "CS50 Introduction to Computer Science",
    "description": "Harvard flagship introduction to computer science and programming",
    "university": "Harvard University",
    "Fees": "$0",
    "Duration": "12 weeks",
    "Level": "Undergraduate"
  },
  {
    "Course Name": "Data Science",
    "description": "Comprehensive data science program covering R, statistics, and machine learning",
    "university": "Harvard University",
    "Fees": "$0",
    "Duration": "9 months",
    "Level": "Certificate"
  }
]